kayaku/__init__.py
kayaku/backend/__init__.py
kayaku/backend/encode.py
kayaku/backend/env.py
kayaku/backend/grammar/json5.lark
kayaku/backend/grammar/wsc.lark
kayaku/backend/transform.py
kayaku/backend/types.py
kayaku/backend/wsc.py
kayaku/doc_parse.py
kayaku/domain.py
kayaku/format.py
kayaku/model.py
kayaku/pretty.py
kayaku/py.typed
kayaku/schema_gen.py
kayaku/spec.py
kayaku/storage.py
kayaku/utils.py
kayaku-0.5.4.dist-info/WHEEL
kayaku-0.5.4.dist-info/METADATA
kayaku-0.5.4.dist-info/licenses/LICENSE
kayaku-0.5.4.dist-info/RECORD
