Metadata-Version: 2.1
Name: kayaku
Version: 0.5.4
Summary: An powerful and flexible configuration solution.
License: MIT
Author-email: BlueGlassBlock <blueglassblock@outlook.com>
Requires-Python: >=3.8,<4.0
Classifier: Development Status :: 4 - Beta
Classifier: Operating System :: OS Independent
Classifier: Typing :: Typed
Requires-Dist: dacite<2.0,>=1.6.0
Requires-Dist: lark[regex]<2.0,>=1.1
Requires-Dist: loguru>=0.7.2
Requires-Dist: typing-extensions<5.0.0,>=4.0.0
